sender/Authenticator.py
sender/Enumerations.py
sender/__init__.py
Squad1CoreSender-1.4.6.dist-info/METADATA
Squad1CoreSender-1.4.6.dist-info/WHEEL
Squad1CoreSender-1.4.6.dist-info/top_level.txt
Squad1CoreSender-1.4.6.dist-info/RECORD
