Metadata-Version: 2.1
Name: Squad1CoreSender
Version: 1.4.6
Summary: paquete utilizado para enviar mensajes entre los módulos y el core en un proyecto académico
Home-page: https://github.com/matiasfelau/sender-python
Author: matiasfelau
Author-email: matiasfelau@gmail.com
Classifier: Programming Language :: Python :: 3
Classifier: License :: OSI Approved :: MIT License
Classifier: Operating System :: OS Independent
Requires-Python: >=3.6
Requires-Dist: pika
